rigorous/__init__.py
rigorous/latex.py
rigorous/syntax.py
rigorous-0.0.1.dist-info/entry_points.txt
rigorous-0.0.1.dist-info/WHEEL
rigorous-0.0.1.dist-info/METADATA
rigorous-0.0.1.dist-info/RECORD
